[{"id":2002,"fullname":"Duncan Niesegen","department":"Sales","dob":"1992-01-27","salary":836655,"age":31},{"id":2003,"fullname":"Terese Pasley","department":"Product Management","dob":"1999-01-10","salary":341904,"age":24},{"id":2004,"fullname":"Henryetta Staines","department":"Research and Development","dob":"1995-03-01","salary":311990,"age":28},{"id":2005,"fullname":"Johann Revett","department":"Marketing","dob":"1998-04-05","salary":515080,"age":25},{"id":2006,"fullname":"Lenci Climar","department":"Product Management","dob":"1998-05-16","salary":630097,"age":25},{"id":2007,"fullname":"Cordula Pegg","department":"Sales","dob":"1997-06-26","salary":842302,"age":26},{"id":2008,"fullname":"Natalina Negri","department":"Human Resources","dob":"2000-07-29","salary":549885,"age":23},{"id":2009,"fullname":"Ethel Willmore","department":"Legal","dob":"2000-05-20","salary":283817,"age":23},{"id":2010,"fullname":"Monte Cornehl","department":"Services","dob":"1992-01-24","salary":545439,"age":31},{"id":2011,"fullname":"Edgard Levinge","department":"Accounting","dob":"2004-04-17","salary":477920,"age":19},{"id":2012,"fullname":"Becki Baskerfield","department":"Product Management","dob":"1998-09-24","salary":132152,"age":25},{"id":2013,"fullname":"Bryon Youd","department":"Engineering","dob":"2001-08-25","salary":888862,"age":22},{"id":2014,"fullname":"Robbie Skurray","department":"Marketing","dob":"1996-05-17","salary":237386,"age":27},{"id":2015,"fullname":"Shaine Maggiori","department":"Sales","dob":"1999-01-06","salary":951987,"age":24},{"id":2016,"fullname":"Shoshana Grimstead","department":"Research and Development","dob":"1997-02-24","salary":805546,"age":26},{"id":2017,"fullname":"Prinz Polin","department":"Engineering","dob":"2003-11-07","salary":654158,"age":20},{"id":2018,"fullname":"Meghann Stratton","department":"Training","dob":"1999-05-20","salary":619663,"age":24},{"id":2019,"fullname":"Rahal Gartshore","department":"Legal","dob":"2003-04-29","salary":668129,"age":20},{"id":2020,"fullname":"Inez Bratten","department":"Research and Development","dob":"1996-07-24","salary":218750,"age":27},{"id":2021,"fullname":"Hattie Fandrich","department":"Business Development","dob":"1995-10-21","salary":787553,"age":28},{"id":2022,"fullname":"Milty Veart","department":"Engineering","dob":"1991-06-19","salary":168162,"age":32},{"id":2023,"fullname":"Celestyna Henlon","department":"Accounting","dob":"2004-08-26","salary":513896,"age":19},{"id":2024,"fullname":"Ruben Drewe","department":"Accounting","dob":"1997-07-30","salary":895811,"age":26},{"id":2025,"fullname":"Kingston McGown","department":"Engineering","dob":"1994-01-26","salary":448174,"age":29},{"id":2026,"fullname":"Frazer Ilem","department":"Marketing","dob":"2001-01-12","salary":956897,"age":22},{"id":2027,"fullname":"Giff Geindre","department":"Legal","dob":"1997-07-18","salary":137864,"age":26},{"id":2028,"fullname":"Andree Lortz","department":"Sales","dob":"2003-11-16","salary":315600,"age":20},{"id":2029,"fullname":"Ingamar Leynagh","department":"Engineering","dob":"2005-11-13","salary":708004,"age":18},{"id":2030,"fullname":"Tuck Sheirlaw","department":"Research and Development","dob":"1991-10-06","salary":606550,"age":32},{"id":2031,"fullname":"Hynda Corriea","department":"Business Development","dob":"1991-06-09","salary":247571,"age":32},{"id":2032,"fullname":"Eleen Priest","department":"Human Resources","dob":"2003-05-10","salary":530263,"age":20},{"id":2033,"fullname":"Felice Bowles","department":"Business Development","dob":"2005-07-20","salary":849341,"age":18},{"id":2034,"fullname":"Byrom Jolin","department":"Product Management","dob":"1995-10-07","salary":804408,"age":28},{"id":2035,"fullname":"Shanon Lynthal","department":"Sales","dob":"2004-03-20","salary":551295,"age":19},{"id":2036,"fullname":"Sylas Farndale","department":"Services","dob":"1994-03-28","salary":666342,"age":29},{"id":2037,"fullname":"Martha Asel","department":"Training","dob":"1995-11-17","salary":646942,"age":28},{"id":2038,"fullname":"Suellen Harroway","department":"Support","dob":"1991-02-14","salary":306979,"age":32},{"id":2039,"fullname":"Sallie Stainsby","department":"Accounting","dob":"2002-11-06","salary":640180,"age":21},{"id":2040,"fullname":"Brietta Hailes","department":"Marketing","dob":"1992-09-11","salary":418402,"age":31},{"id":2041,"fullname":"Christye Huggan","department":"Research and Development","dob":"1992-02-24","salary":661083,"age":31},{"id":2042,"fullname":"Rianon Scraney","department":"Sales","dob":"1994-10-27","salary":223248,"age":29},{"id":2043,"fullname":"Killie Freiberg","department":"Research and Development","dob":"2000-12-20","salary":63962,"age":22},{"id":2044,"fullname":"Philbert Toombes","department":"Research and Development","dob":"2000-03-22","salary":532180,"age":23},{"id":2045,"fullname":"Jolee Ludl","department":"Training","dob":"1997-01-10","salary":181008,"age":26},{"id":2046,"fullname":"Nicky Buxy","department":"Research and Development","dob":"2001-10-25","salary":330115,"age":22},{"id":2047,"fullname":"Abbe Sabbatier","department":"Legal","dob":"2000-11-17","salary":240198,"age":23},{"id":2049,"fullname":"Shannah Gercken","department":"Engineering","dob":"1997-06-02","salary":507386,"age":26},{"id":2050,"fullname":"Vernor Coatham","department":"Sales","dob":"1996-05-31","salary":991173,"age":27},{"fullname":"Ahamed","dob":"2001-07-07","department":"Product Management","salary":41111,"id":2051,"age":22},{"fullname":"batman","dob":"1900-04-08","department":"Research and Development","salary":50000,"id":2052,"age":123},{"fullname":"superman","dob":"2000-08-07","department":"Legal","salary":7000000,"id":2053,"age":23},{"fullname":"spiderman","dob":"2005-04-04","department":"Research and Development","salary":800000,"id":2054,"age":18}]